locstats/__init__.py
locstats/__main__.py
locstats/definitions.py
locstats/languages.json
locstats/loc.py
locstats-1.0.10.dist-info/LICENSE
locstats-1.0.10.dist-info/METADATA
locstats-1.0.10.dist-info/WHEEL
locstats-1.0.10.dist-info/entry_points.txt
locstats-1.0.10.dist-info/top_level.txt
locstats-1.0.10.dist-info/RECORD
