Metadata-Version: 2.1
Name: locstats
Version: 1.0.10
Summary: A statistics tool for your LOC per language
Home-page: https://github.com/kokkonisd/locstats
Author: Dimitri Kokkonis
Author-email: kokkonisd@gmail.com
License: UNKNOWN
Platform: UNKNOWN
Classifier: Programming Language :: Python :: 3
Classifier: License :: OSI Approved :: MIT License
Classifier: Operating System :: OS Independent
Requires-Dist: click
